setup.py
adaptive_binning_chisquared_2sam/__init__.py
adaptive_binning_chisquared_2sam/calling_chi2_example.py
adaptive_binning_chisquared_2sam/chi2_adaptive_binning.py
adaptive_binning_chisquared_2sam/chi2_plots.py
adaptive_binning_chisquared_2sam/chi2_regular_binning.py
adaptive_binning_chisquared_2sam.egg-info/PKG-INFO
adaptive_binning_chisquared_2sam.egg-info/SOURCES.txt
adaptive_binning_chisquared_2sam.egg-info/dependency_links.txt
adaptive_binning_chisquared_2sam.egg-info/not-zip-safe
adaptive_binning_chisquared_2sam.egg-info/requires.txt
adaptive_binning_chisquared_2sam.egg-info/top_level.txt