Metadata-Version: 1.0
Name: adaptive-binning-chisquared-2sam
Version: 0.7
Summary: This repository contains a 2 sample chi squared test the uses adaptive binning using the approach of Roederer et al. (http://onlinelibrary.wiley.com/doi/10.1002/1097-0320(20010901)45:1%3C47::AID-CYTO1143%3E3.0.CO;2-A/epdf)
Home-page: https://github.com/weissercn/adaptive_binning_chisquared_2sam
Author: Constantin Weisser
Author-email: weissercn@gmail.com
License: MIT
Platform: UNKNOWN
